{
"lesson_arr" : [

    {
        "lesson_id" : "00001",
        "lesson_name" : "Basic",
        "lesson_name_translate" : "Pangunahing Pagaaral",
        "parts" : [
           
                    {
                        "description" : "Kumusta!",
                        "choices" : [
                            {
                                "label": "Hello",
                                "audio_src" : "lesson1_p1_c1"

                            },

                            {
                                "label": "Hello",
                                "audio_src" : "lesson1_p1_c2"

                            }
                        ],
                        "image_src" : "lesson1_p1",
                        "instruction_audio" : "lesson1_p1_i",
                        "flag" : false

                    },

            {
                "description" : "Halika't mag-aral tayo ng wikang Ingles!",
                "choices" : [
                    {
                        "label": "Let's study the English language!",
                        "audio_src" : "lesson1_p2_c1"

                    }

                ],
                "image_src" : "lesson1_p1",
                "instruction_audio" : "lesson1_p2_i",
                "flag" : false

            },

            {
                "description" : "Ang ingles ng kumusta ay \"Hello\"",
                "choices" : [
                    {
                        "label": "Hello",
                        "audio_src" : "lesson1_p1_c1"

                    }

                ],
                "image_src" : "lesson1_p1",
                "instruction_audio" : "lesson1_p3_i",
                "flag" : false
            }


                ],
        "quiz" : [

            {
                "question" : "Try question1",
                "instruction_audio" : "quiz1_p1_i",
                "img_src" : "quiz1_img_p1",
                "type" : "audio",
                "question_audio" :  "quiz1_p1_question_audio",
                "choices" : [
                    {
                        "label": "Answer 1",
                        "audio_src" : "quiz1_p1_c1"

                    },
                    {
                        "label": "Answer 2",
                        "audio_src" : "quiz1_p1_c2"

                    },
                    {
                        "label": "Answer 3",
                        "audio_src" : "quiz1_p1_c3"

                    }


                 ],
                "correct_answer" : "Answer 1"
            },
            {
                "question" : "Try question2",
                "instruction_audio" : "quiz1_p2_i",
                "img_src" : "quiz1_img_p2",
                "type" : "visual",
                "question_audio" :  "quiz1_p2_question_audio",
                "choices" : [
                    {
                        "label": "Answer 1",
                        "audio_src" : "quiz1_p2_c1"

                    },
                    {
                        "label": "Answer 2",
                        "audio_src" : "quiz1_p2_c2"

                    },
                    {
                        "label": "Answer 3",
                        "audio_src" : "quiz1_p2_c3"

                    }


                ],
                "correct_answer" : "Answer 2"
            },
            {
                "question" : "Try question3",
                "instruction_audio" : "quiz1_p3_i",
                "img_src" : "quiz1_img_p3",
                "type" : "audio",
                "question_audio" :  "quiz1_p3_question_audio",
                "choices" : [
                    {
                        "label": "Answer 1",
                        "audio_src" : "quiz1_p3_c1"

                    },
                    {
                        "label": "Answer 2",
                        "audio_src" : "quiz1_p3_c2"

                    },
                    {
                        "label": "Answer 3",
                        "audio_src" : "quiz1_p3_c3"

                    }


                ],
                "correct_answer" : "Answer 3"
            }

        ]
    },

    {
        "lesson_id" : "00002",
        "lesson_name" : "Lesson 2",
        "lesson_name_translate" : "Aralin 2",
        "parts" : [

            {
                "description" : "Kumusta!",
                "choices" : [
                    {
                        "label": "Hello",
                        "audio_src" : "lesson1_p1_c1"

                    },

                    {
                        "label": "Hello",
                        "audio_src" : "lesson1_p1_c2"

                    }
                ],
                "image_src" : "lesson1_p1",
                "instruction_audio" : "lesson1_p1_i",
                "flag" : false

            },

            {
                "description" : "Halika't mag-aral tayo ng wikang Ingles!",
                "choices" : [
                    {
                        "label": "Let's study the English language!",
                        "audio_src" : "lesson1_p2_c1"

                    }

                ],
                "image_src" : "lesson1_p1",
                "instruction_audio" : "lesson1_p2_i",
                "flag" : false

            },

            {
                "description" : "Ang ingles ng kumusta ay \"Hello\"",
                "choices" : [
                    {
                        "label": "Hello",
                        "audio_src" : "lesson1_p1_c1"

                    }

                ],
                "image_src" : "lesson1_p1",
                "instruction_audio" : "lesson1_p2_i",
                "flag" : false
            }


        ]
    },

    {
        "lesson_id" : "00003",
        "lesson_name" : "Lesson 3",
        "lesson_name_translate" : "Aralin 3",
        "parts" : [

            {
                "description" : "Kumusta!",
                "choices" : [
                    {
                        "label": "Hello",
                        "audio_src" : "lesson1_p1_c1"

                    },

                    {
                        "label": "Hello",
                        "audio_src" : "lesson1_p1_c2"

                    }
                ],
                "image_src" : "lesson1_p1",
                "instruction_audio" : "lesson1_p1_i",
                "flag" : false

            },

            {
                "description" : "Halika't mag-aral tayo ng wikang Ingles!",
                "choices" : [
                    {
                        "label": "Let's study the English language!",
                        "audio_src" : "lesson1_p2_c1"

                    }

                ],
                "image_src" : "lesson1_p1",
                "instruction_audio" : "lesson1_p2_i",
                "flag" : false

            },

            {
                "description" : "Ang ingles ng kumusta ay \"Hello\"",
                "choices" : [
                    {
                        "label": "Hello",
                        "audio_src" : "lesson1_p1_c1"

                    }

                ],
                "image_src" : "lesson1_p1",
                "instruction_audio" : "lesson1_p2_i",
                "flag" : false
            }


        ]
    }



]

}